coralmc.py
coralmc-1.0.1.dist-info/METADATA
coralmc-1.0.1.dist-info/WHEEL
coralmc-1.0.1.dist-info/RECORD
