Metadata-Version: 2.1
Name: coralmc
Version: 1.0.1
Summary: A Python module to interact with the CoralMC API
Author: letruxux
Author-email: letruxux.t@gmail.com
Requires-Python: >=3.8,<4.0
Classifier: Operating System :: OS Independent
Classifier: Programming Language :: Python :: 3
Classifier: Programming Language :: Python :: 3.8
Classifier: Programming Language :: Python :: 3.9
Classifier: Programming Language :: Python :: 3.10
Classifier: Programming Language :: Python :: 3.11
Requires-Dist: aiohttp (>=3.8.2,<4.0.0)
